<?xml version="1.0" encoding="utf-8"?>
<eml:eml xmlns:eml="eml://ecoinformatics.org/eml-2.1.1" xmlns:xsi="http://www.w3.org/2001/XMLSchema-instance"
         xsi:schemaLocation="eml://ecoinformatics.org/eml-2.1.1 http://rs.gbif.org/schema/eml-gbif-profile/1.1/eml.xsd"
        packageId="10.15468/dl.r49uys"  system="http://gbif.org" scope="system"
  xml:lang="en">

<dataset>
        <alternateIdentifier>0000806-200127171203522</alternateIdentifier>
    <title>GBIF Occurrence Download 10.15468/dl.r49uys</title>
    <creator>
    <individualName>
          <surName>GBIF Download Service</surName>
    </individualName>
<electronicMailAddress>support@gbif.org</electronicMailAddress>    </creator>
    <metadataProvider>
    <individualName>
          <surName>GBIF Download Service</surName>
    </individualName>
<electronicMailAddress>support@gbif.org</electronicMailAddress>    </metadataProvider>
      <pubDate>
      2020-01-28
      </pubDate>
    <language>ENGLISH</language>
    <abstract>
        <para>A dataset containing all occurrences available in GBIF matching the query:
{
  &quot;and&quot; : [ {
    &quot;or&quot; : [ &quot;DatasetKey is Great Backyard Bird Count&quot;, &quot;DatasetKey is iNaturalist Research-grade Observations&quot;, &quot;DatasetKey is WFVZ Bird Collections&quot;, &quot;DatasetKey is NMNH Extant Specimen Records&quot;, &quot;DatasetKey is AMNH Bird Collection&quot;, &quot;DatasetKey is Atlas de las Aves de México: Fase II&quot;, &quot;DatasetKey is Xeno-canto - Bird sounds from around the world&quot;, &quot;DatasetKey is MVZ Bird Collection (Arctos)&quot;, &quot;DatasetKey is University of Michigan Museum of Zoology, Division of Birds&quot;, &quot;DatasetKey is Point Reyes Bird Observatory - Point Counts&quot;, &quot;DatasetKey is Riqueza específica, distribución y abundancia de aves terrestres y marinas en Isla San José, Golfo de California, Baja California Sur, México&quot;, &quot;DatasetKey is NatureServe Network Species Occurrence Data&quot;, &quot;DatasetKey is Museum of Comparative Zoology, Harvard University&quot; ]
  }, {
    &quot;or&quot; : [ &quot;TaxonKey is Polioptila melanura Lawrence, 1857&quot;, &quot;TaxonKey is Toxostoma crissale Henry, 1858&quot;, &quot;TaxonKey is Vireo bellii Audubon, 1844&quot;, &quot;TaxonKey is Auriparus flaviceps (Sundevall, 1850)&quot; ]
  } ]
}
The dataset includes records from the following constituent datasets. The full metadata for each constituent is also included in this archive:
416 records from University of Michigan Museum of Zoology, Division of Birds
494 records from Xeno-canto - Bird sounds from around the world
551 records from AMNH Bird Collection
612 records from Museum of Comparative Zoology, Harvard University
746 records from MVZ Bird Collection (Arctos)
839 records from NMNH Extant Specimen Records
921 records from NatureServe Network Species Occurrence Data
947 records from Riqueza específica, distribución y abundancia de aves terrestres y marinas en Isla San José, Golfo de California, Baja California Sur, México
1188 records from WFVZ Bird Collections
1561 records from Atlas de las Aves de México: Fase II
1667 records from Point Reyes Bird Observatory - Point Counts
3194 records from Great Backyard Bird Count
3501 records from iNaturalist Research-grade Observations
</para>
    </abstract>
      <contact>
    <individualName>
          <surName>GBIF Download Service</surName>
    </individualName>
<electronicMailAddress>support@gbif.org</electronicMailAddress>      </contact>

</dataset>

<additionalMetadata>
    <metadata>
      <gbif>
        <dateStamp>2020-01-28T22:24:36Z</dateStamp>
      <citation identifier="10.15468/dl.r49uys">GBIF Occurrence Download 10.15468/dl.r49uys</citation>
              <physical>
                  <objectName>Darwin Core Archive</objectName>
                  <characterEncoding>UTF-8</characterEncoding>
                  <dataFormat>
                      <externallyDefinedFormat>
                          <formatName>Darwin Core Archive</formatName>
                      </externallyDefinedFormat>
                  </dataFormat>
                  <distribution>
                      <online>
                          <url function="download">http://api.gbif.org/v1/occurrence/download/request/0000806-200127171203522.zip</url>
                      </online>
                  </distribution>
              </physical>
        </gbif>
    </metadata>
</additionalMetadata>

</eml:eml>
